README.rst
setup.py
pygments_base16/__init__.py
pygments_base16/base16-3024.py
pygments_base16/base16-apathy.py
pygments_base16/base16-ashes.py
pygments_base16/base16-atelier-cave-light.py
pygments_base16/base16-atelier-cave.py
pygments_base16/base16-atelier-dune-light.py
pygments_base16/base16-atelier-dune.py
pygments_base16/base16-atelier-estuary-light.py
pygments_base16/base16-atelier-estuary.py
pygments_base16/base16-atelier-forest-light.py
pygments_base16/base16-atelier-forest.py
pygments_base16/base16-atelier-heath-light.py
pygments_base16/base16-atelier-heath.py
pygments_base16/base16-atelier-lakeside-light.py
pygments_base16/base16-atelier-lakeside.py
pygments_base16/base16-atelier-plateau-light.py
pygments_base16/base16-atelier-plateau.py
pygments_base16/base16-atelier-savanna-light.py
pygments_base16/base16-atelier-savanna.py
pygments_base16/base16-atelier-seaside-light.py
pygments_base16/base16-atelier-seaside.py
pygments_base16/base16-atelier-sulphurpool-light.py
pygments_base16/base16-atelier-sulphurpool.py
pygments_base16/base16-bespin.py
pygments_base16/base16-brewer.py
pygments_base16/base16-bright.py
pygments_base16/base16-brushtrees-dark.py
pygments_base16/base16-brushtrees.py
pygments_base16/base16-chalk.py
pygments_base16/base16-circus.py
pygments_base16/base16-classic-dark.py
pygments_base16/base16-classic-light.py
pygments_base16/base16-codeschool.py
pygments_base16/base16-cupcake.py
pygments_base16/base16-cupertino.py
pygments_base16/base16-darktooth.py
pygments_base16/base16-default-dark.py
pygments_base16/base16-default-light.py
pygments_base16/base16-dracula.py
pygments_base16/base16-eighties.py
pygments_base16/base16-embers.py
pygments_base16/base16-flat.py
pygments_base16/base16-github.py
pygments_base16/base16-google-dark.py
pygments_base16/base16-google-light.py
pygments_base16/base16-grayscale-dark.py
pygments_base16/base16-grayscale-light.py
pygments_base16/base16-greenscreen.py
pygments_base16/base16-gruvbox-dark-hard.py
pygments_base16.egg-info/PKG-INFO
pygments_base16.egg-info/SOURCES.txt
pygments_base16.egg-info/dependency_links.txt
pygments_base16.egg-info/entry_points.txt
pygments_base16.egg-info/requires.txt
pygments_base16.egg-info/top_level.txt