Metadata-Version: 1.1
Name: pygments-base16
Version: 1.0.3
Summary: Base16 styles for Pygments
Home-page: https://github.com/mohd-akram/base16-pygments
Author: Mohamed Akram
Author-email: mohd.akram@outlook.com
License: MIT
Keywords: pygments syntax highlighting
Platform: UNKNOWN
Classifier: License :: OSI Approved :: MIT License
Classifier: Intended Audience :: Developers
Classifier: Intended Audience :: End Users/Desktop
Classifier: Intended Audience :: System Administrators
Classifier: Development Status :: 5 - Production/Stable
Classifier: Programming Language :: Python :: 3
Classifier: Programming Language :: Python :: 3.5
Classifier: Programming Language :: Python :: 3.6
Classifier: Operating System :: OS Independent
Classifier: Topic :: Text Processing :: Filters
Classifier: Topic :: Utilities
